AUTHORS.rst
CHANGES.rst
LICENSE.rst
termlog/__init__.py
termlog/colors.py
termlog/config.py
termlog/constants.py
termlog/decorations.py
termlog/formatting.py
termlog/interpret.py
termlog/message.py
termlog/palettes.py
termlog/terminal.py
termlog/tests/README.md
termlog/tests/__init__.py
termlog/tests/test_beautify.py
termlog/tests/test_colors.py
termlog/tests/test_echo.py
termlog/tests/test_interpret.py
termlog/tests/test_message.py
termlog/tests/test_set_config.py
termlog/tests/test_strip_escape.py
termlog/tests/test_true_color_support.py
termlog-1.4.0.dist-info/LICENSE.rst
termlog-1.4.0.dist-info/WHEEL
termlog-1.4.0.dist-info/METADATA
termlog-1.4.0.dist-info/RECORD
