Metadata-Version: 2.1
Name: termlog
Version: 1.4.0
Summary: A Terminal logging library
Home-page: https://github.com/brianbruggeman/termlog
License: MIT
Keywords: terminal,logging,color,json
Author: Brian Bruggeman
Author-email: 1350114+brianbruggeman@users.noreply.github.com
Requires-Python: >=3.8,<4.0
Classifier: Development Status :: 4 - Beta
Classifier: Environment :: Console
Classifier: Intended Audience :: Developers
Classifier: License :: OSI Approved :: MIT License
Classifier: Natural Language :: English
Classifier: Operating System :: OS Independent
Classifier: Programming Language :: Python :: 3
Classifier: Programming Language :: Python :: 3.10
Classifier: Programming Language :: Python :: 3.8
Classifier: Programming Language :: Python :: 3.9
Classifier: Typing :: Typed
Requires-Dist: pygments (>=2.6.1,<3.0.0)
Project-URL: Repository, https://github.com/brianbruggeman/termlog
